{"categories":[{"id":"77ffd8ca-95d6-4dc1-8e6c-93fa20e780e1","name":"Clothing","createdAt":1629621573591,"updatedAt":1629621573591},{"id":"d29c4b1c-539e-413e-b9a7-971c02313048","name":"Kids","createdAt":1629621573591,"updatedAt":1629621573591},{"id":"7d3d0a92-b04b-4c36-8aae-62e86ba1df05","name":"Books","createdAt":1629621573591,"updatedAt":1629621573591},{"id":"6de508c0-9845-49ea-88e2-fea941159ebb","name":"Electronics","createdAt":1629621573591,"updatedAt":1629621573591},{"id":"690ee0cb-30c9-4938-b599-a93de3c6e767","name":"Shoes","createdAt":1629621573591,"updatedAt":1629621573591}],"product":[{"categoryID":"77ffd8ca-95d6-4dc1-8e6c-93fa20e780e1","id":"03dbdc40-9737-4418-9cbc-edab0de5f63a","name":"Sleek Concrete Table","price":725,"color":"gold","description":"Andy shoes are designed to keeping in mind durability as well as trends, the most stylish range of shoes & sandals","createdAt":1629621573592,"updatedAt":1629621573592,"thumbnail":"http://placeimg.com/400/400"},{"categoryID":"77ffd8ca-95d6-4dc1-8e6c-93fa20e780e1","id":"17183076-ccd7-4ea4-9216-c75d59a02a5d","name":"Small Concrete Hat","price":144,"color":"turquoise","description":"The Apollotech B340 is an affordable wireless mouse with reliable connectivity, 12 months battery life and modern design","createdAt":1629621573592,"updatedAt":1629621573592,"thumbnail":"http://placeimg.com/400/400"},{"categoryID":"77ffd8ca-95d6-4dc1-8e6c-93fa20e780e1","id":"95c1d96c-95cc-4413-9cdf-5e725dedbfb3","name":"Practical Plastic Ball","price":770,"color":"green","description":"The automobile layout consists of a front-engine design, with transaxle-type transmissions mounted at the rear of the engine and four wheel drive","createdAt":1629621573592,"updatedAt":1629621573592,"thumbnail":"http://placeimg.com/400/400"},{"categoryID":"77ffd8ca-95d6-4dc1-8e6c-93fa20e780e1","id":"e81f3b9b-347e-4911-825b-2197b4eda496","name":"Sleek Metal Tuna","price":938,"color":"olive","description":"The Nagasaki Lander is the trademarked name of several series of Nagasaki sport bikes, that started with the 1984 ABC800J","createdAt":1629621573592,"updatedAt":1629621573592,"thumbnail":"http://placeimg.com/400/400"},{"categoryID":"77ffd8ca-95d6-4dc1-8e6c-93fa20e780e1","id":"30368ab4-aa41-4b18-b33b-32858b52198c","name":"Generic Soft Soap","price":580,"color":"black","description":"Ergonomic executive chair upholstered in bonded black leather and PVC padded seat and back for all-day comfort and support","createdAt":1629621573592,"updatedAt":1629621573592,"thumbnail":"http://placeimg.com/400/400"},{"categoryID":"77ffd8ca-95d6-4dc1-8e6c-93fa20e780e1","id":"2abf8705-69eb-4363-88d9-872f7da2255d","name":"Handmade Cotton Chicken","price":6,"color":"black","description":"The beautiful range of Apple Naturalé that has an exciting mix of natural ingredients. With the Goodness of 100% Natural Ingredients","createdAt":1629621573592,"updatedAt":1629621573592,"thumbnail":"http://placeimg.com/400/400"}],"profile":{"name":"Thanh"}}